fds/__init__.py
fds/sdk/__init__.py
fds/sdk/ETFProfileandPrices/__init__.py
fds/sdk/ETFProfileandPrices/api_client.py
fds/sdk/ETFProfileandPrices/configuration.py
fds/sdk/ETFProfileandPrices/exceptions.py
fds/sdk/ETFProfileandPrices/model_utils.py
fds/sdk/ETFProfileandPrices/rest.py
fds/sdk/ETFProfileandPrices/api/__init__.py
fds/sdk/ETFProfileandPrices/api/factset_api.py
fds/sdk/ETFProfileandPrices/apis/__init__.py
fds/sdk/ETFProfileandPrices/model/__init__.py
fds/sdk/ETFProfileandPrices/model/attributes_member.py
fds/sdk/ETFProfileandPrices/model/cursor_based_pagination_output_object.py
fds/sdk/ETFProfileandPrices/model/cursor_based_pagination_output_object_without_total.py
fds/sdk/ETFProfileandPrices/model/error_meta_object.py
fds/sdk/ETFProfileandPrices/model/error_object.py
fds/sdk/ETFProfileandPrices/model/inline_response200.py
fds/sdk/ETFProfileandPrices/model/inline_response2001.py
fds/sdk/ETFProfileandPrices/model/inline_response20010.py
fds/sdk/ETFProfileandPrices/model/inline_response20010_data.py
fds/sdk/ETFProfileandPrices/model/inline_response20010_data_index_change.py
fds/sdk/ETFProfileandPrices/model/inline_response20010_data_risk.py
fds/sdk/ETFProfileandPrices/model/inline_response20010_data_security_lending.py
fds/sdk/ETFProfileandPrices/model/inline_response20011.py
fds/sdk/ETFProfileandPrices/model/inline_response20011_data.py
fds/sdk/ETFProfileandPrices/model/inline_response20012.py
fds/sdk/ETFProfileandPrices/model/inline_response20012_data.py
fds/sdk/ETFProfileandPrices/model/inline_response20012_data_beta.py
fds/sdk/ETFProfileandPrices/model/inline_response20012_data_efficiency.py
fds/sdk/ETFProfileandPrices/model/inline_response20012_data_fit.py
fds/sdk/ETFProfileandPrices/model/inline_response20012_data_tradability.py
fds/sdk/ETFProfileandPrices/model/inline_response20013.py
fds/sdk/ETFProfileandPrices/model/inline_response20013_data.py
fds/sdk/ETFProfileandPrices/model/inline_response20013_data_block_trade.py
fds.sdk.ETFProfileandPrices-0.10.15.dist-info/LICENSE
fds.sdk.ETFProfileandPrices-0.10.15.dist-info/METADATA
fds.sdk.ETFProfileandPrices-0.10.15.dist-info/WHEEL
fds.sdk.ETFProfileandPrices-0.10.15.dist-info/top_level.txt
fds.sdk.ETFProfileandPrices-0.10.15.dist-info/RECORD
